setup.py
src/digimat/__init__.py
src/digimat.ip01.egg-info/PKG-INFO
src/digimat.ip01.egg-info/SOURCES.txt
src/digimat.ip01.egg-info/dependency_links.txt
src/digimat.ip01.egg-info/namespace_packages.txt
src/digimat.ip01.egg-info/not-zip-safe
src/digimat.ip01.egg-info/requires.txt
src/digimat.ip01.egg-info/top_level.txt
src/digimat/ip01/__init__.py
src/digimat/ip01/ip01.py