Metadata-Version: 1.0
Name: digimat.ip01
Version: 0.1.0
Summary: Digimat IP01
Home-page: UNKNOWN
Author: Frederic Hess
Author-email: fhess@splust.ch
License: PSF
Platform: UNKNOWN
